<?xml version="1.0" encoding="UTF-8"?>

<!-- generated on 2025-09-17 10:06:05 by Eclipse SUMO GUI Version 1.24.0
<sumoConfiguration xmlns:xsi="http://www.w3.org/2001/XMLSchema-instance" xsi:noNamespaceSchemaLocation="http://sumo.dlr.de/xsd/sumoConfiguration.xsd">

    <input>
        <net-file value="map6/RL.net.xml"/>
        <route-files value="map6/trips.trips.xml"/>
        <additional-files value="map6/RL.add.xml"/>
    </input>

    <traci_server>
        <remote-port value="58856"/>
    </traci_server>

</sumoConfiguration>
-->

<detector xmlns:xsi="http://www.w3.org/2001/XMLSchema-instance" xsi:noNamespaceSchemaLocation="http://sumo.dlr.de/xsd/det_e2_file.xsd">
   <interval begin="0.00" end="300.00" id="e2_14" sampledSeconds="609.13" nVehEntered="15" nVehLeft="10" nVehSeen="15" meanSpeed="2.12" meanTimeLoss="34.18" meanOccupancy="10.09" maxOccupancy="40.00" meanMaxJamLengthInVehicles="1.50" meanMaxJamLengthInMeters="9.58" maxJamLengthInVehicles="6" maxJamLengthInMeters="42.57" jamLengthInVehiclesSum="449" jamLengthInMetersSum="2872.68" meanHaltingDuration="41.82" maxHaltingDuration="109.00" haltingDurationSum="460.00" meanIntervalHaltingDuration="41.82" maxIntervalHaltingDuration="109.00" intervalHaltingDurationSum="460.00" startedHalts="11.00" meanVehicleNumber="2.07" maxVehicleNumber="8" />
   <interval begin="300.00" end="600.00" id="e2_14" sampledSeconds="1598.10" nVehEntered="28" nVehLeft="22" nVehSeen="33" meanSpeed="1.58" meanTimeLoss="42.78" meanOccupancy="26.49" maxOccupancy="55.00" meanMaxJamLengthInVehicles="4.29" meanMaxJamLengthInMeters="30.30" maxJamLengthInVehicles="11" maxJamLengthInMeters="80.04" jamLengthInVehiclesSum="1286" jamLengthInMetersSum="9091.20" meanHaltingDuration="57.19" maxHaltingDuration="138.00" haltingDurationSum="1487.00" meanIntervalHaltingDuration="50.35" maxIntervalHaltingDuration="138.00" intervalHaltingDurationSum="1309.00" startedHalts="23.00" meanVehicleNumber="5.40" maxVehicleNumber="11" />
   <interval begin="600.00" end="900.00" id="e2_14" sampledSeconds="2522.29" nVehEntered="15" nVehLeft="26" nVehSeen="26" meanSpeed="0.77" meanTimeLoss="91.30" meanOccupancy="41.29" maxOccupancy="61.36" meanMaxJamLengthInVehicles="7.33" meanMaxJamLengthInMeters="52.49" maxJamLengthInVehicles="13" maxJamLengthInMeters="91.37" jamLengthInVehiclesSum="2198" jamLengthInMetersSum="15748.16" meanHaltingDuration="112.61" maxHaltingDuration="142.00" haltingDurationSum="2590.00" meanIntervalHaltingDuration="96.09" maxIntervalHaltingDuration="142.00" intervalHaltingDurationSum="2210.00" startedHalts="12.00" meanVehicleNumber="8.46" maxVehicleNumber="13" />
   <interval begin="900.00" end="1200.00" id="e2_14" sampledSeconds="815.30" nVehEntered="16" nVehLeft="10" nVehSeen="16" meanSpeed="1.72" meanTimeLoss="44.43" meanOccupancy="13.49" maxOccupancy="30.00" meanMaxJamLengthInVehicles="2.14" meanMaxJamLengthInMeters="14.43" maxJamLengthInVehicles="6" maxJamLengthInMeters="42.59" jamLengthInVehiclesSum="643" jamLengthInMetersSum="4327.58" meanHaltingDuration="50.46" maxHaltingDuration="98.00" haltingDurationSum="656.00" meanIntervalHaltingDuration="50.46" maxIntervalHaltingDuration="98.00" intervalHaltingDurationSum="656.00" startedHalts="13.00" meanVehicleNumber="2.77" maxVehicleNumber="6" />
   <interval begin="1200.00" end="1500.00" id="e2_14" sampledSeconds="1717.88" nVehEntered="28" nVehLeft="32" nVehSeen="34" meanSpeed="1.65" meanTimeLoss="43.98" meanOccupancy="28.31" maxOccupancy="60.00" meanMaxJamLengthInVehicles="4.33" meanMaxJamLengthInMeters="30.79" maxJamLengthInVehicles="11" maxJamLengthInMeters="81.20" jamLengthInVehiclesSum="1299" jamLengthInMetersSum="9236.41" meanHaltingDuration="74.33" maxHaltingDuration="139.00" haltingDurationSum="1784.00" meanIntervalHaltingDuration="54.88" maxIntervalHaltingDuration="139.00" intervalHaltingDurationSum="1317.00" startedHalts="18.00" meanVehicleNumber="5.82" maxVehicleNumber="12" />
   <interval begin="1500.00" end="1800.00" id="e2_14" sampledSeconds="1714.30" nVehEntered="20" nVehLeft="11" nVehSeen="22" meanSpeed="0.83" meanTimeLoss="72.98" meanOccupancy="28.39" maxOccupancy="60.71" meanMaxJamLengthInVehicles="5.06" meanMaxJamLengthInMeters="35.76" maxJamLengthInVehicles="13" maxJamLengthInMeters="92.21" jamLengthInVehiclesSum="1518" jamLengthInMetersSum="10727.35" meanHaltingDuration="77.05" maxHaltingDuration="136.00" haltingDurationSum="1541.00" meanIntervalHaltingDuration="76.85" maxIntervalHaltingDuration="136.00" intervalHaltingDurationSum="1537.00" startedHalts="19.00" meanVehicleNumber="5.77" maxVehicleNumber="13" />
   <interval begin="1800.00" end="2100.00" id="e2_14" sampledSeconds="1381.25" nVehEntered="20" nVehLeft="27" nVehSeen="31" meanSpeed="1.86" meanTimeLoss="38.43" meanOccupancy="22.68" maxOccupancy="50.82" meanMaxJamLengthInVehicles="3.41" meanMaxJamLengthInMeters="23.62" maxJamLengthInVehicles="9" maxJamLengthInMeters="65.01" jamLengthInVehiclesSum="1024" jamLengthInMetersSum="7084.65" meanHaltingDuration="73.95" maxHaltingDuration="140.00" haltingDurationSum="1627.00" meanIntervalHaltingDuration="47.14" maxIntervalHaltingDuration="140.00" intervalHaltingDurationSum="1037.00" startedHalts="13.00" meanVehicleNumber="4.69" maxVehicleNumber="11" />
   <interval begin="2100.00" end="2400.00" id="e2_14" sampledSeconds="1171.62" nVehEntered="20" nVehLeft="23" nVehSeen="24" meanSpeed="1.75" meanTimeLoss="42.30" meanOccupancy="19.33" maxOccupancy="40.00" meanMaxJamLengthInVehicles="3.03" meanMaxJamLengthInMeters="20.97" maxJamLengthInVehicles="8" maxJamLengthInMeters="57.55" jamLengthInVehiclesSum="908" jamLengthInMetersSum="6290.09" meanHaltingDuration="69.70" maxHaltingDuration="139.00" haltingDurationSum="1185.00" meanIntervalHaltingDuration="54.18" maxIntervalHaltingDuration="139.00" intervalHaltingDurationSum="921.00" startedHalts="13.00" meanVehicleNumber="3.97" maxVehicleNumber="8" />
   <interval begin="2400.00" end="2700.00" id="e2_14" sampledSeconds="1682.45" nVehEntered="21" nVehLeft="14" nVehSeen="22" meanSpeed="1.05" meanTimeLoss="70.46" meanOccupancy="27.89" maxOccupancy="55.00" meanMaxJamLengthInVehicles="4.73" meanMaxJamLengthInMeters="33.28" maxJamLengthInVehicles="11" maxJamLengthInMeters="80.02" jamLengthInVehiclesSum="1420" jamLengthInMetersSum="9984.19" meanHaltingDuration="65.55" maxHaltingDuration="131.00" haltingDurationSum="1442.00" meanIntervalHaltingDuration="65.50" maxIntervalHaltingDuration="130.00" intervalHaltingDurationSum="1441.00" startedHalts="21.00" meanVehicleNumber="5.66" maxVehicleNumber="12" />
   <interval begin="2700.00" end="3000.00" id="e2_14" sampledSeconds="1148.39" nVehEntered="18" nVehLeft="23" nVehSeen="26" meanSpeed="1.79" meanTimeLoss="38.20" meanOccupancy="18.94" maxOccupancy="40.00" meanMaxJamLengthInVehicles="3.02" meanMaxJamLengthInMeters="20.87" maxJamLengthInVehicles="8" maxJamLengthInMeters="57.55" jamLengthInVehiclesSum="905" jamLengthInMetersSum="6262.35" meanHaltingDuration="80.67" maxHaltingDuration="141.00" haltingDurationSum="1452.00" meanIntervalHaltingDuration="50.89" maxIntervalHaltingDuration="141.00" intervalHaltingDurationSum="916.00" startedHalts="11.00" meanVehicleNumber="3.88" maxVehicleNumber="8" />
   <interval begin="3000.00" end="3300.00" id="e2_14" sampledSeconds="1533.73" nVehEntered="25" nVehLeft="28" nVehSeen="28" meanSpeed="1.64" meanTimeLoss="48.09" meanOccupancy="25.28" maxOccupancy="54.07" meanMaxJamLengthInVehicles="3.87" meanMaxJamLengthInMeters="27.19" maxJamLengthInVehicles="10" maxJamLengthInMeters="73.87" jamLengthInVehiclesSum="1162" jamLengthInMetersSum="8157.12" meanHaltingDuration="56.82" maxHaltingDuration="128.00" haltingDurationSum="1250.00" meanIntervalHaltingDuration="53.68" maxIntervalHaltingDuration="126.00" intervalHaltingDurationSum="1181.00" startedHalts="19.00" meanVehicleNumber="5.20" maxVehicleNumber="11" />
   <interval begin="3300.00" end="3600.00" id="e2_14" sampledSeconds="1151.40" nVehEntered="14" nVehLeft="10" nVehSeen="14" meanSpeed="1.12" meanTimeLoss="75.56" meanOccupancy="19.12" maxOccupancy="50.00" meanMaxJamLengthInVehicles="3.25" meanMaxJamLengthInMeters="22.73" maxJamLengthInVehicles="9" maxJamLengthInMeters="65.03" jamLengthInVehiclesSum="976" jamLengthInMetersSum="6818.35" meanHaltingDuration="76.08" maxHaltingDuration="121.00" haltingDurationSum="989.00" meanIntervalHaltingDuration="76.08" maxIntervalHaltingDuration="121.00" intervalHaltingDurationSum="989.00" startedHalts="13.00" meanVehicleNumber="3.88" maxVehicleNumber="10" />
   <interval begin="3600.00" end="3900.00" id="e2_14" sampledSeconds="1224.52" nVehEntered="20" nVehLeft="21" nVehSeen="24" meanSpeed="1.62" meanTimeLoss="44.71" meanOccupancy="20.21" maxOccupancy="57.94" meanMaxJamLengthInVehicles="3.10" meanMaxJamLengthInMeters="21.52" maxJamLengthInVehicles="11" maxJamLengthInMeters="80.01" jamLengthInVehiclesSum="930" jamLengthInMetersSum="6457.04" meanHaltingDuration="56.35" maxHaltingDuration="128.00" haltingDurationSum="1127.00" meanIntervalHaltingDuration="47.35" maxIntervalHaltingDuration="128.00" intervalHaltingDurationSum="947.00" startedHalts="17.00" meanVehicleNumber="4.14" maxVehicleNumber="12" />
   <interval begin="3900.00" end="4200.00" id="e2_14" sampledSeconds="1856.40" nVehEntered="23" nVehLeft="22" nVehSeen="26" meanSpeed="1.20" meanTimeLoss="65.02" meanOccupancy="30.71" maxOccupancy="55.00" meanMaxJamLengthInVehicles="5.08" meanMaxJamLengthInMeters="35.98" maxJamLengthInVehicles="11" maxJamLengthInMeters="80.02" jamLengthInVehiclesSum="1523" jamLengthInMetersSum="10792.69" meanHaltingDuration="66.88" maxHaltingDuration="137.00" haltingDurationSum="1605.00" meanIntervalHaltingDuration="64.38" maxIntervalHaltingDuration="133.00" intervalHaltingDurationSum="1545.00" startedHalts="22.00" meanVehicleNumber="6.26" maxVehicleNumber="11" />
   <interval begin="4200.00" end="4500.00" id="e2_14" sampledSeconds="1604.77" nVehEntered="18" nVehLeft="13" nVehSeen="22" meanSpeed="0.97" meanTimeLoss="67.63" meanOccupancy="26.67" maxOccupancy="45.00" meanMaxJamLengthInVehicles="4.61" meanMaxJamLengthInMeters="32.47" maxJamLengthInVehicles="9" maxJamLengthInMeters="65.02" jamLengthInVehiclesSum="1384" jamLengthInMetersSum="9739.74" meanHaltingDuration="70.20" maxHaltingDuration="138.00" haltingDurationSum="1404.00" meanIntervalHaltingDuration="70.20" maxIntervalHaltingDuration="138.00" intervalHaltingDurationSum="1404.00" startedHalts="20.00" meanVehicleNumber="5.39" maxVehicleNumber="9" />
   <interval begin="4500.00" end="4800.00" id="e2_14" sampledSeconds="3768.11" nVehEntered="5" nVehLeft="1" nVehSeen="14" meanSpeed="0.04" meanTimeLoss="268.46" meanOccupancy="59.66" maxOccupancy="60.82" meanMaxJamLengthInVehicles="12.28" meanMaxJamLengthInMeters="86.58" maxJamLengthInVehicles="13" maxJamLengthInMeters="90.83" jamLengthInVehiclesSum="3717" jamLengthInMetersSum="26185.94" meanHaltingDuration="161.22" maxHaltingDuration="301.00" haltingDurationSum="4353.00" meanIntervalHaltingDuration="131.41" maxIntervalHaltingDuration="198.00" intervalHaltingDurationSum="3548.00" startedHalts="19.00" meanVehicleNumber="12.57" maxVehicleNumber="13" />
   <interval begin="4800.00" end="5100.00" id="e2_14" sampledSeconds="3721.54" nVehEntered="11" nVehLeft="11" nVehSeen="24" meanSpeed="0.29" meanTimeLoss="151.77" meanOccupancy="58.12" maxOccupancy="60.82" meanMaxJamLengthInVehicles="11.65" meanMaxJamLengthInMeters="81.30" maxJamLengthInVehicles="13" maxJamLengthInMeters="90.83" jamLengthInVehiclesSum="3495" jamLengthInMetersSum="24395.52" meanHaltingDuration="151.09" maxHaltingDuration="232.00" haltingDurationSum="4835.00" meanIntervalHaltingDuration="109.81" maxIntervalHaltingDuration="149.00" intervalHaltingDurationSum="3514.00" startedHalts="19.00" meanVehicleNumber="12.44" maxVehicleNumber="13" />
   <interval begin="5100.00" end="5400.00" id="e2_14" sampledSeconds="591.37" nVehEntered="9" nVehLeft="20" nVehSeen="22" meanSpeed="2.61" meanTimeLoss="21.51" meanOccupancy="9.39" maxOccupancy="60.82" meanMaxJamLengthInVehicles="1.31" meanMaxJamLengthInMeters="7.90" maxJamLengthInVehicles="13" maxJamLengthInMeters="90.83" jamLengthInVehiclesSum="392" jamLengthInMetersSum="2369.26" meanHaltingDuration="130.65" maxHaltingDuration="156.00" haltingDurationSum="2221.00" meanIntervalHaltingDuration="23.29" maxIntervalHaltingDuration="139.00" intervalHaltingDurationSum="396.00" startedHalts="4.00" meanVehicleNumber="2.02" maxVehicleNumber="13" />
   <interval begin="5400.00" end="5700.00" id="e2_14" sampledSeconds="210.91" nVehEntered="3" nVehLeft="5" nVehSeen="5" meanSpeed="1.51" meanTimeLoss="37.47" meanOccupancy="3.50" maxOccupancy="15.00" meanMaxJamLengthInVehicles="0.59" meanMaxJamLengthInMeters="3.77" maxJamLengthInVehicles="3" maxJamLengthInMeters="20.18" jamLengthInVehiclesSum="176" jamLengthInMetersSum="1130.38" meanHaltingDuration="79.33" maxHaltingDuration="115.00" haltingDurationSum="238.00" meanIntervalHaltingDuration="59.00" maxIntervalHaltingDuration="75.00" intervalHaltingDurationSum="177.00" startedHalts="1.00" meanVehicleNumber="0.71" maxVehicleNumber="3" />
   <interval begin="5700.00" end="6000.00" id="e2_14" sampledSeconds="0.00" nVehEntered="0" nVehLeft="0" nVehSeen="0" meanSpeed="-1.00" meanTimeLoss="-1.00" meanOccupancy="0.00" maxOccupancy="0.00" meanMaxJamLengthInVehicles="0.00" meanMaxJamLengthInMeters="0.00" maxJamLengthInVehicles="0" maxJamLengthInMeters="0.00" jamLengthInVehiclesSum="0" jamLengthInMetersSum="0.00" meanHaltingDuration="0.00" maxHaltingDuration="0.00" haltingDurationSum="0.00" meanIntervalHaltingDuration="0.00" maxIntervalHaltingDuration="0.00" intervalHaltingDurationSum="0.00" startedHalts="0.00" meanVehicleNumber="0.00" maxVehicleNumber="0" />
   <interval begin="6000.00" end="6300.00" id="e2_14" sampledSeconds="0.00" nVehEntered="0" nVehLeft="0" nVehSeen="0" meanSpeed="-1.00" meanTimeLoss="-1.00" meanOccupancy="0.00" maxOccupancy="0.00" meanMaxJamLengthInVehicles="0.00" meanMaxJamLengthInMeters="0.00" maxJamLengthInVehicles="0" maxJamLengthInMeters="0.00" jamLengthInVehiclesSum="0" jamLengthInMetersSum="0.00" meanHaltingDuration="0.00" maxHaltingDuration="0.00" haltingDurationSum="0.00" meanIntervalHaltingDuration="0.00" maxIntervalHaltingDuration="0.00" intervalHaltingDurationSum="0.00" startedHalts="0.00" meanVehicleNumber="0.00" maxVehicleNumber="0" />
   <interval begin="6300.00" end="6594.00" id="e2_14" sampledSeconds="0.00" nVehEntered="0" nVehLeft="0" nVehSeen="0" meanSpeed="-1.00" meanTimeLoss="-1.00" meanOccupancy="0.00" maxOccupancy="0.00" meanMaxJamLengthInVehicles="0.00" meanMaxJamLengthInMeters="0.00" maxJamLengthInVehicles="0" maxJamLengthInMeters="0.00" jamLengthInVehiclesSum="0" jamLengthInMetersSum="0.00" meanHaltingDuration="0.00" maxHaltingDuration="0.00" haltingDurationSum="0.00" meanIntervalHaltingDuration="0.00" maxIntervalHaltingDuration="0.00" intervalHaltingDurationSum="0.00" startedHalts="0.00" meanVehicleNumber="0.00" maxVehicleNumber="0" />
</detector>
